Metadata-Version: 1.0
Name: jay-malde-distributions
Version: 0.1
Summary: Gaussian and Binomial distributions
Home-page: UNKNOWN
Author: Jay Malde
Author-email: maldejay77@gmail.com
License: UNKNOWN
Platform: UNKNOWN
